blockstack_zones/__init__.py
blockstack_zones/configs.py
blockstack_zones/exceptions.py
blockstack_zones/make_zone_file.py
blockstack_zones/parse_zone_file.py
blockstack_zones/record_processors.py
blockstack_zones_py3-0.19.1.dist-info/LICENSE
blockstack_zones_py3-0.19.1.dist-info/METADATA
blockstack_zones_py3-0.19.1.dist-info/WHEEL
blockstack_zones_py3-0.19.1.dist-info/top_level.txt
blockstack_zones_py3-0.19.1.dist-info/RECORD
