Metadata-Version: 2.1
Name: blockstack-zones-py3
Version: 0.19.1
Summary: Library for creating and parsing DNS zone files
Home-page: https://github.com/jaywink/zone-file-py
Author: Blockstack Developers
Author-email: hello@onename.com
Maintainer: Jason Robinson
Maintainer-email: mail@jasonrobinson.me
License: MIT
Keywords: dns zone file zonefile parse create
Platform: UNKNOWN
Classifier: Intended Audience :: Developers
Classifier: License :: OSI Approved :: MIT License
Classifier: Operating System :: OS Independent
Classifier: Programming Language :: Python
Classifier: Programming Language :: Python :: 3 :: Only
Classifier: Programming Language :: Python :: 3.7
Classifier: Programming Language :: Python :: 3.8
Classifier: Topic :: Internet
Classifier: Topic :: Software Development :: Libraries :: Python Modules
